tno/zkp/commitment_schemes/pedersen/__init__.py
tno/zkp/commitment_schemes/pedersen/pedersen_commitment_scheme.py
tno/zkp/commitment_schemes/pedersen/py.typed
tno/zkp/commitment_schemes/pedersen/test/__init__.py
tno/zkp/commitment_schemes/pedersen/test/conftest.py
tno/zkp/commitment_schemes/pedersen/test/test_compressed_pedersen_commitment.py
tno/zkp/commitment_schemes/pedersen/test/test_pedersen_commitment.py
tno/zkp/commitment_schemes/pedersen/test/test_pedersen_functionality.py
tno/zkp/commitment_schemes/pedersen/test/test_pedersen_input.py
tno/zkp/commitment_schemes/pedersen/test/test_pedersen_output.py
tno.zkp.commitment_schemes.pedersen-0.2.0.dist-info/LICENSE
tno.zkp.commitment_schemes.pedersen-0.2.0.dist-info/METADATA
tno.zkp.commitment_schemes.pedersen-0.2.0.dist-info/WHEEL
tno.zkp.commitment_schemes.pedersen-0.2.0.dist-info/top_level.txt
tno.zkp.commitment_schemes.pedersen-0.2.0.dist-info/RECORD
