Metadata-Version: 2.1
Name: tno.zkp.commitment_schemes.pedersen
Version: 0.2.0
Summary: ZKP Pedersen Commitment Scheme module
Author-email: TNO PET Lab <petlab@tno.nl>
Maintainer-email: TNO PET Lab <petlab@tno.nl>
License: Apache License, Version 2.0
Project-URL: Homepage, https://pet.tno.nl/
Project-URL: Documentation, https://docs.pet.tno.nl/zkp/commitment_schemes/pedersen/0.2.0
Project-URL: Source, https://github.com/TNO-ZKP/commitment_schemes.pedersen
Keywords: TNO,ZKP,zero-knowledge proofs
Platform: any
Classifier: License :: OSI Approved :: Apache Software License
Classifier: Programming Language :: Python :: 3
Classifier: Operating System :: OS Independent
Classifier: Intended Audience :: Developers
Classifier: Intended Audience :: Information Technology
Classifier: Intended Audience :: Science/Research
Classifier: Typing :: Typed
Classifier: Topic :: Security :: Cryptography
Requires-Python: >=3.9
License-File: LICENSE
Requires-Dist: tno.zkp.templates~=0.1
Requires-Dist: tno.mpc.encryption_schemes.utils~=0.11
Requires-Dist: sympy
Provides-Extra: gmpy
Requires-Dist: tno.mpc.encryption_schemes.utils[gmpy]; extra == "gmpy"
Provides-Extra: tests
Requires-Dist: pytest>=8.1; extra == "tests"
Requires-Dist: pytest_asyncio; extra == "tests"
Requires-Dist: tno.zkp.templates[test]; extra == "tests"
